[
  {
    "name": "Connect_ID",
    "mode": "",
    "type": "STRING",
    "description": "",
    "fields": []
  },
  {
    "name": "d_143615646_d_248868659_d_283900611",
    "mode": "",
    "type": "STRING",
    "description": "",
    "fields": []
  },
  {
    "name": "d_143615646_d_248868659_d_313097539",
    "mode": "",
    "type": "STRING",
    "description": "",
    "fields": []
  },
  {
    "name": "d_143615646_d_248868659_d_453343022",
    "mode": "",
    "type": "STRING",
    "description": "",
    "fields": []
  },
  {
    "name": "d_143615646_d_248868659_d_472864016",
    "mode": "",
    "type": "STRING",
    "description": "",
    "fields": []
  },
  {
    "name": "d_143615646_d_248868659_d_684617815",
    "mode": "",
    "type": "STRING",
    "description": "",
    "fields": []
  },
  {
    "name": "d_143615646_d_248868659_d_728366619",
    "mode": "",
    "type": "STRING",
    "description": "",
    "fields": []
  },
  {
    "name": "d_143615646_d_248868659_d_742806035",
    "mode": "",
    "type": "STRING",
    "description": "",
    "fields": []
  },
  {
    "name": "d_143615646_d_248868659_d_757246707",
    "mode": "",
    "type": "STRING",
    "description": "",
    "fields": []
  },
  {
    "name": "d_143615646_d_248868659_d_982885431",
    "mode": "",
    "type": "STRING",
    "description": "",
    "fields": []
  },
  {
    "name": "d_143615646_d_338286049",
    "mode": "",
    "type": "STRING",
    "description": "",
    "fields": []
  },
  {
    "name": "d_143615646_d_536710547",
    "mode": "",
    "type": "STRING",
    "description": "",
    "fields": []
  },
  {
    "name": "d_143615646_d_593843561",
    "mode": "",
    "type": "STRING",
    "description": "",
    "fields": []
  },
  {
    "name": "d_143615646_d_678857215",
    "mode": "",
    "type": "STRING",
    "description": "",
    "fields": []
  },
  {
    "name": "d_143615646_d_762124027",
    "mode": "",
    "type": "STRING",
    "description": "",
    "fields": []
  },
  {
    "name": "d_143615646_d_825582494",
    "mode": "",
    "type": "STRING",
    "description": "",
    "fields": []
  },
  {
    "name": "d_143615646_d_826941471",
    "mode": "",
    "type": "STRING",
    "description": "",
    "fields": []
  },
  {
    "name": "d_143615646_d_883732523",
    "mode": "",
    "type": "STRING",
    "description": "",
    "fields": []
  },
  {
    "name": "d_143615646_d_926457119",
    "mode": "",
    "type": "STRING",
    "description": "",
    "fields": []
  },
  {
    "name": "d_223999569_d_593843561",
    "mode": "",
    "type": "STRING",
    "description": "",
    "fields": []
  },
  {
    "name": "d_223999569_d_678857215",
    "mode": "",
    "type": "STRING",
    "description": "",
    "fields": []
  },
  {
    "name": "d_223999569_d_762124027",
    "mode": "",
    "type": "STRING",
    "description": "",
    "fields": []
  },
  {
    "name": "d_223999569_d_825582494",
    "mode": "",
    "type": "STRING",
    "description": "",
    "fields": []
  },
  {
    "name": "d_232343615_d_248868659_d_102695484",
    "mode": "",
    "type": "STRING",
    "description": "",
    "fields": []
  },
  {
    "name": "d_232343615_d_248868659_d_242307474",
    "mode": "",
    "type": "STRING",
    "description": "",
    "fields": []
  },
  {
    "name": "d_232343615_d_248868659_d_283900611",
    "mode": "",
    "type": "STRING",
    "description": "",
    "fields": []
  },
  {
    "name": "d_232343615_d_248868659_d_313097539",
    "mode": "",
    "type": "STRING",
    "description": "",
    "fields": []
  },
  {
    "name": "d_232343615_d_248868659_d_453343022",
    "mode": "",
    "type": "STRING",
    "description": "",
    "fields": []
  },
  {
    "name": "d_232343615_d_248868659_d_472864016",
    "mode": "",
    "type": "STRING",
    "description": "",
    "fields": []
  },
  {
    "name": "d_232343615_d_248868659_d_550088682",
    "mode": "",
    "type": "STRING",
    "description": "",
    "fields": []
  },
  {
    "name": "d_232343615_d_248868659_d_561005927",
    "mode": "",
    "type": "STRING",
    "description": "",
    "fields": []
  },
  {
    "name": "d_232343615_d_248868659_d_635875253",
    "mode": "",
    "type": "STRING",
    "description": "",
    "fields": []
  },
  {
    "name": "d_232343615_d_248868659_d_654002184",
    "mode": "",
    "type": "STRING",
    "description": "",
    "fields": []
  },
  {
    "name": "d_232343615_d_248868659_d_684617815",
    "mode": "",
    "type": "STRING",
    "description": "",
    "fields": []
  },
  {
    "name": "d_232343615_d_248868659_d_690540566",
    "mode": "",
    "type": "STRING",
    "description": "",
    "fields": []
  },
  {
    "name": "d_232343615_d_248868659_d_728366619",
    "mode": "",
    "type": "STRING",
    "description": "",
    "fields": []
  },
  {
    "name": "d_232343615_d_248868659_d_757246707",
    "mode": "",
    "type": "STRING",
    "description": "",
    "fields": []
  },
  {
    "name": "d_232343615_d_248868659_d_777486216",
    "mode": "",
    "type": "STRING",
    "description": "",
    "fields": []
  },
  {
    "name": "d_232343615_d_248868659_d_810960823",
    "mode": "",
    "type": "STRING",
    "description": "",
    "fields": []
  },
  {
    "name": "d_232343615_d_248868659_d_861162895",
    "mode": "",
    "type": "STRING",
    "description": "",
    "fields": []
  },
  {
    "name": "d_232343615_d_248868659_d_912088602",
    "mode": "",
    "type": "STRING",
    "description": "",
    "fields": []
  },
  {
    "name": "d_232343615_d_248868659_d_937362785",
    "mode": "",
    "type": "STRING",
    "description": "",
    "fields": []
  },
  {
    "name": "d_232343615_d_248868659_d_982885431",
    "mode": "",
    "type": "STRING",
    "description": "",
    "fields": []
  },
  {
    "name": "d_232343615_d_536710547",
    "mode": "",
    "type": "STRING",
    "description": "",
    "fields": []
  },
  {
    "name": "d_232343615_d_593843561",
    "mode": "",
    "type": "STRING",
    "description": "",
    "fields": []
  },
  {
    "name": "d_232343615_d_678857215",
    "mode": "",
    "type": "STRING",
    "description": "",
    "fields": []
  },
  {
    "name": "d_232343615_d_762124027",
    "mode": "",
    "type": "STRING",
    "description": "",
    "fields": []
  },
  {
    "name": "d_232343615_d_825582494",
    "mode": "",
    "type": "STRING",
    "description": "",
    "fields": []
  },
  {
    "name": "d_232343615_d_926457119",
    "mode": "",
    "type": "STRING",
    "description": "",
    "fields": []
  },
  {
    "name": "d_260133861",
    "mode": "",
    "type": "STRING",
    "description": "",
    "fields": []
  },
  {
    "name": "d_299553921_d_248868659_d_102695484",
    "mode": "",
    "type": "STRING",
    "description": "",
    "fields": []
  },
  {
    "name": "d_299553921_d_248868659_d_242307474",
    "mode": "",
    "type": "STRING",
    "description": "",
    "fields": []
  },
  {
    "name": "d_299553921_d_248868659_d_283900611",
    "mode": "",
    "type": "STRING",
    "description": "",
    "fields": []
  },
  {
    "name": "d_299553921_d_248868659_d_313097539",
    "mode": "",
    "type": "STRING",
    "description": "",
    "fields": []
  },
  {
    "name": "d_299553921_d_248868659_d_453343022",
    "mode": "",
    "type": "STRING",
    "description": "",
    "fields": []
  },
  {
    "name": "d_299553921_d_248868659_d_472864016",
    "mode": "",
    "type": "STRING",
    "description": "",
    "fields": []
  },
  {
    "name": "d_299553921_d_248868659_d_550088682",
    "mode": "",
    "type": "STRING",
    "description": "",
    "fields": []
  },
  {
    "name": "d_299553921_d_248868659_d_561005927",
    "mode": "",
    "type": "STRING",
    "description": "",
    "fields": []
  },
  {
    "name": "d_299553921_d_248868659_d_635875253",
    "mode": "",
    "type": "STRING",
    "description": "",
    "fields": []
  },
  {
    "name": "d_299553921_d_248868659_d_654002184",
    "mode": "",
    "type": "STRING",
    "description": "",
    "fields": []
  },
  {
    "name": "d_299553921_d_248868659_d_684617815",
    "mode": "",
    "type": "STRING",
    "description": "",
    "fields": []
  },
  {
    "name": "d_299553921_d_248868659_d_690540566",
    "mode": "",
    "type": "STRING",
    "description": "",
    "fields": []
  },
  {
    "name": "d_299553921_d_248868659_d_728366619",
    "mode": "",
    "type": "STRING",
    "description": "",
    "fields": []
  },
  {
    "name": "d_299553921_d_248868659_d_757246707",
    "mode": "",
    "type": "STRING",
    "description": "",
    "fields": []
  },
  {
    "name": "d_299553921_d_248868659_d_777486216",
    "mode": "",
    "type": "STRING",
    "description": "",
    "fields": []
  },
  {
    "name": "d_299553921_d_248868659_d_810960823",
    "mode": "",
    "type": "STRING",
    "description": "",
    "fields": []
  },
  {
    "name": "d_299553921_d_248868659_d_861162895",
    "mode": "",
    "type": "STRING",
    "description": "",
    "fields": []
  },
  {
    "name": "d_299553921_d_248868659_d_912088602",
    "mode": "",
    "type": "STRING",
    "description": "",
    "fields": []
  },
  {
    "name": "d_299553921_d_248868659_d_937362785",
    "mode": "",
    "type": "STRING",
    "description": "",
    "fields": []
  },
  {
    "name": "d_299553921_d_248868659_d_982885431",
    "mode": "",
    "type": "STRING",
    "description": "",
    "fields": []
  },
  {
    "name": "d_299553921_d_338286049",
    "mode": "",
    "type": "STRING",
    "description": "",
    "fields": []
  },
  {
    "name": "d_299553921_d_536710547",
    "mode": "",
    "type": "STRING",
    "description": "",
    "fields": []
  },
  {
    "name": "d_299553921_d_593843561",
    "mode": "",
    "type": "STRING",
    "description": "",
    "fields": []
  },
  {
    "name": "d_299553921_d_678857215",
    "mode": "",
    "type": "STRING",
    "description": "",
    "fields": []
  },
  {
    "name": "d_299553921_d_762124027",
    "mode": "",
    "type": "STRING",
    "description": "",
    "fields": []
  },
  {
    "name": "d_299553921_d_825582494",
    "mode": "",
    "type": "STRING",
    "description": "",
    "fields": []
  },
  {
    "name": "d_299553921_d_883732523",
    "mode": "",
    "type": "STRING",
    "description": "",
    "fields": []
  },
  {
    "name": "d_299553921_d_926457119",
    "mode": "",
    "type": "STRING",
    "description": "",
    "fields": []
  },
  {
    "name": "d_331584571",
    "mode": "",
    "type": "STRING",
    "description": "",
    "fields": []
  },
  {
    "name": "d_338570265",
    "mode": "",
    "type": "STRING",
    "description": "",
    "fields": []
  },
  {
    "name": "d_376960806_d_248868659_d_102695484",
    "mode": "",
    "type": "STRING",
    "description": "",
    "fields": []
  },
  {
    "name": "d_376960806_d_248868659_d_242307474",
    "mode": "",
    "type": "STRING",
    "description": "",
    "fields": []
  },
  {
    "name": "d_376960806_d_248868659_d_283900611",
    "mode": "",
    "type": "STRING",
    "description": "",
    "fields": []
  },
  {
    "name": "d_376960806_d_248868659_d_313097539",
    "mode": "",
    "type": "STRING",
    "description": "",
    "fields": []
  },
  {
    "name": "d_376960806_d_248868659_d_453343022",
    "mode": "",
    "type": "STRING",
    "description": "",
    "fields": []
  },
  {
    "name": "d_376960806_d_248868659_d_472864016",
    "mode": "",
    "type": "STRING",
    "description": "",
    "fields": []
  },
  {
    "name": "d_376960806_d_248868659_d_550088682",
    "mode": "",
    "type": "STRING",
    "description": "",
    "fields": []
  },
  {
    "name": "d_376960806_d_248868659_d_561005927",
    "mode": "",
    "type": "STRING",
    "description": "",
    "fields": []
  },
  {
    "name": "d_376960806_d_248868659_d_635875253",
    "mode": "",
    "type": "STRING",
    "description": "",
    "fields": []
  },
  {
    "name": "d_376960806_d_248868659_d_654002184",
    "mode": "",
    "type": "STRING",
    "description": "",
    "fields": []
  },
  {
    "name": "d_376960806_d_248868659_d_684617815",
    "mode": "",
    "type": "STRING",
    "description": "",
    "fields": []
  },
  {
    "name": "d_376960806_d_248868659_d_690540566",
    "mode": "",
    "type": "STRING",
    "description": "",
    "fields": []
  },
  {
    "name": "d_376960806_d_248868659_d_728366619",
    "mode": "",
    "type": "STRING",
    "description": "",
    "fields": []
  },
  {
    "name": "d_376960806_d_248868659_d_757246707",
    "mode": "",
    "type": "STRING",
    "description": "",
    "fields": []
  },
  {
    "name": "d_376960806_d_248868659_d_777486216",
    "mode": "",
    "type": "STRING",
    "description": "",
    "fields": []
  },
  {
    "name": "d_376960806_d_248868659_d_810960823",
    "mode": "",
    "type": "STRING",
    "description": "",
    "fields": []
  },
  {
    "name": "d_376960806_d_248868659_d_861162895",
    "mode": "",
    "type": "STRING",
    "description": "",
    "fields": []
  },
  {
    "name": "d_376960806_d_248868659_d_912088602",
    "mode": "",
    "type": "STRING",
    "description": "",
    "fields": []
  },
  {
    "name": "d_376960806_d_248868659_d_937362785",
    "mode": "",
    "type": "STRING",
    "description": "",
    "fields": []
  },
  {
    "name": "d_376960806_d_248868659_d_982885431",
    "mode": "",
    "type": "STRING",
    "description": "",
    "fields": []
  },
  {
    "name": "d_376960806_d_536710547",
    "mode": "",
    "type": "STRING",
    "description": "",
    "fields": []
  },
  {
    "name": "d_376960806_d_593843561",
    "mode": "",
    "type": "STRING",
    "description": "",
    "fields": []
  },
  {
    "name": "d_376960806_d_678857215",
    "mode": "",
    "type": "STRING",
    "description": "",
    "fields": []
  },
  {
    "name": "d_376960806_d_762124027",
    "mode": "",
    "type": "STRING",
    "description": "",
    "fields": []
  },
  {
    "name": "d_376960806_d_825582494",
    "mode": "",
    "type": "STRING",
    "description": "",
    "fields": []
  },
  {
    "name": "d_376960806_d_926457119",
    "mode": "",
    "type": "STRING",
    "description": "",
    "fields": []
  },
  {
    "name": "d_387108065",
    "mode": "",
    "type": "STRING",
    "description": "",
    "fields": []
  },
  {
    "name": "d_410912345",
    "mode": "",
    "type": "STRING",
    "description": "",
    "fields": []
  },
  {
    "name": "d_454453939_d_248868659_d_242307474",
    "mode": "",
    "type": "STRING",
    "description": "",
    "fields": []
  },
  {
    "name": "d_454453939_d_248868659_d_283900611",
    "mode": "",
    "type": "STRING",
    "description": "",
    "fields": []
  },
  {
    "name": "d_454453939_d_248868659_d_313097539",
    "mode": "",
    "type": "STRING",
    "description": "",
    "fields": []
  },
  {
    "name": "d_454453939_d_248868659_d_453343022",
    "mode": "",
    "type": "STRING",
    "description": "",
    "fields": []
  },
  {
    "name": "d_454453939_d_248868659_d_472864016",
    "mode": "",
    "type": "STRING",
    "description": "",
    "fields": []
  },
  {
    "name": "d_454453939_d_248868659_d_550088682",
    "mode": "",
    "type": "STRING",
    "description": "",
    "fields": []
  },
  {
    "name": "d_454453939_d_248868659_d_684617815",
    "mode": "",
    "type": "STRING",
    "description": "",
    "fields": []
  },
  {
    "name": "d_454453939_d_248868659_d_690540566",
    "mode": "",
    "type": "STRING",
    "description": "",
    "fields": []
  },
  {
    "name": "d_454453939_d_248868659_d_728366619",
    "mode": "",
    "type": "STRING",
    "description": "",
    "fields": []
  },
  {
    "name": "d_454453939_d_248868659_d_757246707",
    "mode": "",
    "type": "STRING",
    "description": "",
    "fields": []
  },
  {
    "name": "d_454453939_d_248868659_d_777486216",
    "mode": "",
    "type": "STRING",
    "description": "",
    "fields": []
  },
  {
    "name": "d_454453939_d_248868659_d_810960823",
    "mode": "",
    "type": "STRING",
    "description": "",
    "fields": []
  },
  {
    "name": "d_454453939_d_248868659_d_982885431",
    "mode": "",
    "type": "STRING",
    "description": "",
    "fields": []
  },
  {
    "name": "d_454453939_d_338286049",
    "mode": "",
    "type": "STRING",
    "description": "",
    "fields": []
  },
  {
    "name": "d_454453939_d_536710547",
    "mode": "",
    "type": "STRING",
    "description": "",
    "fields": []
  },
  {
    "name": "d_454453939_d_593843561",
    "mode": "",
    "type": "STRING",
    "description": "",
    "fields": []
  },
  {
    "name": "d_454453939_d_678857215",
    "mode": "",
    "type": "STRING",
    "description": "",
    "fields": []
  },
  {
    "name": "d_454453939_d_762124027",
    "mode": "",
    "type": "STRING",
    "description": "",
    "fields": []
  },
  {
    "name": "d_454453939_d_825582494",
    "mode": "",
    "type": "STRING",
    "description": "",
    "fields": []
  },
  {
    "name": "d_454453939_d_883732523",
    "mode": "",
    "type": "STRING",
    "description": "",
    "fields": []
  },
  {
    "name": "d_454453939_d_926457119",
    "mode": "",
    "type": "STRING",
    "description": "",
    "fields": []
  },
  {
    "name": "d_505347689_d_248868659_d_242307474",
    "mode": "",
    "type": "STRING",
    "description": "",
    "fields": []
  },
  {
    "name": "d_505347689_d_248868659_d_283900611",
    "mode": "",
    "type": "STRING",
    "description": "",
    "fields": []
  },
  {
    "name": "d_505347689_d_248868659_d_313097539",
    "mode": "",
    "type": "STRING",
    "description": "",
    "fields": []
  },
  {
    "name": "d_505347689_d_248868659_d_453343022",
    "mode": "",
    "type": "STRING",
    "description": "",
    "fields": []
  },
  {
    "name": "d_505347689_d_248868659_d_472864016",
    "mode": "",
    "type": "STRING",
    "description": "",
    "fields": []
  },
  {
    "name": "d_505347689_d_248868659_d_550088682",
    "mode": "",
    "type": "STRING",
    "description": "",
    "fields": []
  },
  {
    "name": "d_505347689_d_248868659_d_684617815",
    "mode": "",
    "type": "STRING",
    "description": "",
    "fields": []
  },
  {
    "name": "d_505347689_d_248868659_d_690540566",
    "mode": "",
    "type": "STRING",
    "description": "",
    "fields": []
  },
  {
    "name": "d_505347689_d_248868659_d_728366619",
    "mode": "",
    "type": "STRING",
    "description": "",
    "fields": []
  },
  {
    "name": "d_505347689_d_248868659_d_757246707",
    "mode": "",
    "type": "STRING",
    "description": "",
    "fields": []
  },
  {
    "name": "d_505347689_d_248868659_d_777486216",
    "mode": "",
    "type": "STRING",
    "description": "",
    "fields": []
  },
  {
    "name": "d_505347689_d_248868659_d_810960823",
    "mode": "",
    "type": "STRING",
    "description": "",
    "fields": []
  },
  {
    "name": "d_505347689_d_248868659_d_982885431",
    "mode": "",
    "type": "STRING",
    "description": "",
    "fields": []
  },
  {
    "name": "d_505347689_d_338286049",
    "mode": "",
    "type": "STRING",
    "description": "",
    "fields": []
  },
  {
    "name": "d_505347689_d_536710547",
    "mode": "",
    "type": "STRING",
    "description": "",
    "fields": []
  },
  {
    "name": "d_505347689_d_593843561",
    "mode": "",
    "type": "STRING",
    "description": "",
    "fields": []
  },
  {
    "name": "d_505347689_d_678857215",
    "mode": "",
    "type": "STRING",
    "description": "",
    "fields": []
  },
  {
    "name": "d_505347689_d_762124027",
    "mode": "",
    "type": "STRING",
    "description": "",
    "fields": []
  },
  {
    "name": "d_505347689_d_825582494",
    "mode": "",
    "type": "STRING",
    "description": "",
    "fields": []
  },
  {
    "name": "d_505347689_d_883732523",
    "mode": "",
    "type": "STRING",
    "description": "",
    "fields": []
  },
  {
    "name": "d_505347689_d_926457119",
    "mode": "",
    "type": "STRING",
    "description": "",
    "fields": []
  },
  {
    "name": "d_556788178",
    "mode": "",
    "type": "STRING",
    "description": "",
    "fields": []
  },
  {
    "name": "d_589588440_d_248868659_d_102695484",
    "mode": "",
    "type": "STRING",
    "description": "",
    "fields": []
  },
  {
    "name": "d_589588440_d_248868659_d_242307474",
    "mode": "",
    "type": "STRING",
    "description": "",
    "fields": []
  },
  {
    "name": "d_589588440_d_248868659_d_283900611",
    "mode": "",
    "type": "STRING",
    "description": "",
    "fields": []
  },
  {
    "name": "d_589588440_d_248868659_d_313097539",
    "mode": "",
    "type": "STRING",
    "description": "",
    "fields": []
  },
  {
    "name": "d_589588440_d_248868659_d_453343022",
    "mode": "",
    "type": "STRING",
    "description": "",
    "fields": []
  },
  {
    "name": "d_589588440_d_248868659_d_472864016",
    "mode": "",
    "type": "STRING",
    "description": "",
    "fields": []
  },
  {
    "name": "d_589588440_d_248868659_d_550088682",
    "mode": "",
    "type": "STRING",
    "description": "",
    "fields": []
  },
  {
    "name": "d_589588440_d_248868659_d_561005927",
    "mode": "",
    "type": "STRING",
    "description": "",
    "fields": []
  },
  {
    "name": "d_589588440_d_248868659_d_635875253",
    "mode": "",
    "type": "STRING",
    "description": "",
    "fields": []
  },
  {
    "name": "d_589588440_d_248868659_d_654002184",
    "mode": "",
    "type": "STRING",
    "description": "",
    "fields": []
  },
  {
    "name": "d_589588440_d_248868659_d_684617815",
    "mode": "",
    "type": "STRING",
    "description": "",
    "fields": []
  },
  {
    "name": "d_589588440_d_248868659_d_690540566",
    "mode": "",
    "type": "STRING",
    "description": "",
    "fields": []
  },
  {
    "name": "d_589588440_d_248868659_d_728366619",
    "mode": "",
    "type": "STRING",
    "description": "",
    "fields": []
  },
  {
    "name": "d_589588440_d_248868659_d_757246707",
    "mode": "",
    "type": "STRING",
    "description": "",
    "fields": []
  },
  {
    "name": "d_589588440_d_248868659_d_777486216",
    "mode": "",
    "type": "STRING",
    "description": "",
    "fields": []
  },
  {
    "name": "d_589588440_d_248868659_d_810960823",
    "mode": "",
    "type": "STRING",
    "description": "",
    "fields": []
  },
  {
    "name": "d_589588440_d_248868659_d_861162895",
    "mode": "",
    "type": "STRING",
    "description": "",
    "fields": []
  },
  {
    "name": "d_589588440_d_248868659_d_912088602",
    "mode": "",
    "type": "STRING",
    "description": "",
    "fields": []
  },
  {
    "name": "d_589588440_d_248868659_d_937362785",
    "mode": "",
    "type": "STRING",
    "description": "",
    "fields": []
  },
  {
    "name": "d_589588440_d_248868659_d_982885431",
    "mode": "",
    "type": "STRING",
    "description": "",
    "fields": []
  },
  {
    "name": "d_589588440_d_536710547",
    "mode": "",
    "type": "STRING",
    "description": "",
    "fields": []
  },
  {
    "name": "d_589588440_d_593843561",
    "mode": "",
    "type": "STRING",
    "description": "",
    "fields": []
  },
  {
    "name": "d_589588440_d_678857215",
    "mode": "",
    "type": "STRING",
    "description": "",
    "fields": []
  },
  {
    "name": "d_589588440_d_762124027",
    "mode": "",
    "type": "STRING",
    "description": "",
    "fields": []
  },
  {
    "name": "d_589588440_d_825582494",
    "mode": "",
    "type": "STRING",
    "description": "",
    "fields": []
  },
  {
    "name": "d_589588440_d_926457119",
    "mode": "",
    "type": "STRING",
    "description": "",
    "fields": []
  },
  {
    "name": "d_646899796",
    "mode": "",
    "type": "STRING",
    "description": "",
    "fields": []
  },
  {
    "name": "d_650516960",
    "mode": "",
    "type": "STRING",
    "description": "",
    "fields": []
  },
  {
    "name": "d_652357376_d_248868659_d_242307474",
    "mode": "",
    "type": "STRING",
    "description": "",
    "fields": []
  },
  {
    "name": "d_652357376_d_248868659_d_283900611",
    "mode": "",
    "type": "STRING",
    "description": "",
    "fields": []
  },
  {
    "name": "d_652357376_d_248868659_d_313097539",
    "mode": "",
    "type": "STRING",
    "description": "",
    "fields": []
  },
  {
    "name": "d_652357376_d_248868659_d_453343022",
    "mode": "",
    "type": "STRING",
    "description": "",
    "fields": []
  },
  {
    "name": "d_652357376_d_248868659_d_472864016",
    "mode": "",
    "type": "STRING",
    "description": "",
    "fields": []
  },
  {
    "name": "d_652357376_d_248868659_d_550088682",
    "mode": "",
    "type": "STRING",
    "description": "",
    "fields": []
  },
  {
    "name": "d_652357376_d_248868659_d_684617815",
    "mode": "",
    "type": "STRING",
    "description": "",
    "fields": []
  },
  {
    "name": "d_652357376_d_248868659_d_690540566",
    "mode": "",
    "type": "STRING",
    "description": "",
    "fields": []
  },
  {
    "name": "d_652357376_d_248868659_d_728366619",
    "mode": "",
    "type": "STRING",
    "description": "",
    "fields": []
  },
  {
    "name": "d_652357376_d_248868659_d_757246707",
    "mode": "",
    "type": "STRING",
    "description": "",
    "fields": []
  },
  {
    "name": "d_652357376_d_248868659_d_777486216",
    "mode": "",
    "type": "STRING",
    "description": "",
    "fields": []
  },
  {
    "name": "d_652357376_d_248868659_d_810960823",
    "mode": "",
    "type": "STRING",
    "description": "",
    "fields": []
  },
  {
    "name": "d_652357376_d_248868659_d_982885431",
    "mode": "",
    "type": "STRING",
    "description": "",
    "fields": []
  },
  {
    "name": "d_652357376_d_338286049",
    "mode": "",
    "type": "STRING",
    "description": "",
    "fields": []
  },
  {
    "name": "d_652357376_d_536710547",
    "mode": "",
    "type": "STRING",
    "description": "",
    "fields": []
  },
  {
    "name": "d_652357376_d_593843561",
    "mode": "",
    "type": "STRING",
    "description": "",
    "fields": []
  },
  {
    "name": "d_652357376_d_678857215",
    "mode": "",
    "type": "STRING",
    "description": "",
    "fields": []
  },
  {
    "name": "d_652357376_d_762124027",
    "mode": "",
    "type": "STRING",
    "description": "",
    "fields": []
  },
  {
    "name": "d_652357376_d_825582494",
    "mode": "",
    "type": "STRING",
    "description": "",
    "fields": []
  },
  {
    "name": "d_652357376_d_883732523",
    "mode": "",
    "type": "STRING",
    "description": "",
    "fields": []
  },
  {
    "name": "d_652357376_d_926457119",
    "mode": "",
    "type": "STRING",
    "description": "",
    "fields": []
  },
  {
    "name": "d_677469051_d_248868659_d_242307474",
    "mode": "",
    "type": "STRING",
    "description": "",
    "fields": []
  },
  {
    "name": "d_677469051_d_248868659_d_283900611",
    "mode": "",
    "type": "STRING",
    "description": "",
    "fields": []
  },
  {
    "name": "d_677469051_d_248868659_d_313097539",
    "mode": "",
    "type": "STRING",
    "description": "",
    "fields": []
  },
  {
    "name": "d_677469051_d_248868659_d_453343022",
    "mode": "",
    "type": "STRING",
    "description": "",
    "fields": []
  },
  {
    "name": "d_677469051_d_248868659_d_472864016",
    "mode": "",
    "type": "STRING",
    "description": "",
    "fields": []
  },
  {
    "name": "d_677469051_d_248868659_d_550088682",
    "mode": "",
    "type": "STRING",
    "description": "",
    "fields": []
  },
  {
    "name": "d_677469051_d_248868659_d_684617815",
    "mode": "",
    "type": "STRING",
    "description": "",
    "fields": []
  },
  {
    "name": "d_677469051_d_248868659_d_690540566",
    "mode": "",
    "type": "STRING",
    "description": "",
    "fields": []
  },
  {
    "name": "d_677469051_d_248868659_d_728366619",
    "mode": "",
    "type": "STRING",
    "description": "",
    "fields": []
  },
  {
    "name": "d_677469051_d_248868659_d_757246707",
    "mode": "",
    "type": "STRING",
    "description": "",
    "fields": []
  },
  {
    "name": "d_677469051_d_248868659_d_777486216",
    "mode": "",
    "type": "STRING",
    "description": "",
    "fields": []
  },
  {
    "name": "d_677469051_d_248868659_d_810960823",
    "mode": "",
    "type": "STRING",
    "description": "",
    "fields": []
  },
  {
    "name": "d_677469051_d_248868659_d_982885431",
    "mode": "",
    "type": "STRING",
    "description": "",
    "fields": []
  },
  {
    "name": "d_677469051_d_536710547",
    "mode": "",
    "type": "STRING",
    "description": "",
    "fields": []
  },
  {
    "name": "d_677469051_d_593843561",
    "mode": "",
    "type": "STRING",
    "description": "",
    "fields": []
  },
  {
    "name": "d_677469051_d_678857215",
    "mode": "",
    "type": "STRING",
    "description": "",
    "fields": []
  },
  {
    "name": "d_677469051_d_762124027",
    "mode": "",
    "type": "STRING",
    "description": "",
    "fields": []
  },
  {
    "name": "d_677469051_d_825582494",
    "mode": "",
    "type": "STRING",
    "description": "",
    "fields": []
  },
  {
    "name": "d_677469051_d_926457119",
    "mode": "",
    "type": "STRING",
    "description": "",
    "fields": []
  },
  {
    "name": "d_678166505",
    "mode": "",
    "type": "STRING",
    "description": "",
    "fields": []
  },
  {
    "name": "d_683613884_d_248868659_d_242307474",
    "mode": "",
    "type": "STRING",
    "description": "",
    "fields": []
  },
  {
    "name": "d_683613884_d_248868659_d_283900611",
    "mode": "",
    "type": "STRING",
    "description": "",
    "fields": []
  },
  {
    "name": "d_683613884_d_248868659_d_313097539",
    "mode": "",
    "type": "STRING",
    "description": "",
    "fields": []
  },
  {
    "name": "d_683613884_d_248868659_d_453343022",
    "mode": "",
    "type": "STRING",
    "description": "",
    "fields": []
  },
  {
    "name": "d_683613884_d_248868659_d_472864016",
    "mode": "",
    "type": "STRING",
    "description": "",
    "fields": []
  },
  {
    "name": "d_683613884_d_248868659_d_550088682",
    "mode": "",
    "type": "STRING",
    "description": "",
    "fields": []
  },
  {
    "name": "d_683613884_d_248868659_d_684617815",
    "mode": "",
    "type": "STRING",
    "description": "",
    "fields": []
  },
  {
    "name": "d_683613884_d_248868659_d_690540566",
    "mode": "",
    "type": "STRING",
    "description": "",
    "fields": []
  },
  {
    "name": "d_683613884_d_248868659_d_728366619",
    "mode": "",
    "type": "STRING",
    "description": "",
    "fields": []
  },
  {
    "name": "d_683613884_d_248868659_d_757246707",
    "mode": "",
    "type": "STRING",
    "description": "",
    "fields": []
  },
  {
    "name": "d_683613884_d_248868659_d_777486216",
    "mode": "",
    "type": "STRING",
    "description": "",
    "fields": []
  },
  {
    "name": "d_683613884_d_248868659_d_810960823",
    "mode": "",
    "type": "STRING",
    "description": "",
    "fields": []
  },
  {
    "name": "d_683613884_d_248868659_d_982885431",
    "mode": "",
    "type": "STRING",
    "description": "",
    "fields": []
  },
  {
    "name": "d_683613884_d_536710547",
    "mode": "",
    "type": "STRING",
    "description": "",
    "fields": []
  },
  {
    "name": "d_683613884_d_593843561",
    "mode": "",
    "type": "STRING",
    "description": "",
    "fields": []
  },
  {
    "name": "d_683613884_d_678857215",
    "mode": "",
    "type": "STRING",
    "description": "",
    "fields": []
  },
  {
    "name": "d_683613884_d_762124027",
    "mode": "",
    "type": "STRING",
    "description": "",
    "fields": []
  },
  {
    "name": "d_683613884_d_825582494",
    "mode": "",
    "type": "STRING",
    "description": "",
    "fields": []
  },
  {
    "name": "d_683613884_d_926457119",
    "mode": "",
    "type": "STRING",
    "description": "",
    "fields": []
  },
  {
    "name": "d_687158491",
    "mode": "",
    "type": "STRING",
    "description": "",
    "fields": []
  },
  {
    "name": "d_703954371_d_248868659_d_102695484",
    "mode": "",
    "type": "STRING",
    "description": "",
    "fields": []
  },
  {
    "name": "d_703954371_d_248868659_d_242307474",
    "mode": "",
    "type": "STRING",
    "description": "",
    "fields": []
  },
  {
    "name": "d_703954371_d_248868659_d_283900611",
    "mode": "",
    "type": "STRING",
    "description": "",
    "fields": []
  },
  {
    "name": "d_703954371_d_248868659_d_313097539",
    "mode": "",
    "type": "STRING",
    "description": "",
    "fields": []
  },
  {
    "name": "d_703954371_d_248868659_d_453343022",
    "mode": "",
    "type": "STRING",
    "description": "",
    "fields": []
  },
  {
    "name": "d_703954371_d_248868659_d_472864016",
    "mode": "",
    "type": "STRING",
    "description": "",
    "fields": []
  },
  {
    "name": "d_703954371_d_248868659_d_550088682",
    "mode": "",
    "type": "STRING",
    "description": "",
    "fields": []
  },
  {
    "name": "d_703954371_d_248868659_d_561005927",
    "mode": "",
    "type": "STRING",
    "description": "",
    "fields": []
  },
  {
    "name": "d_703954371_d_248868659_d_635875253",
    "mode": "",
    "type": "STRING",
    "description": "",
    "fields": []
  },
  {
    "name": "d_703954371_d_248868659_d_654002184",
    "mode": "",
    "type": "STRING",
    "description": "",
    "fields": []
  },
  {
    "name": "d_703954371_d_248868659_d_684617815",
    "mode": "",
    "type": "STRING",
    "description": "",
    "fields": []
  },
  {
    "name": "d_703954371_d_248868659_d_690540566",
    "mode": "",
    "type": "STRING",
    "description": "",
    "fields": []
  },
  {
    "name": "d_703954371_d_248868659_d_728366619",
    "mode": "",
    "type": "STRING",
    "description": "",
    "fields": []
  },
  {
    "name": "d_703954371_d_248868659_d_757246707",
    "mode": "",
    "type": "STRING",
    "description": "",
    "fields": []
  },
  {
    "name": "d_703954371_d_248868659_d_777486216",
    "mode": "",
    "type": "STRING",
    "description": "",
    "fields": []
  },
  {
    "name": "d_703954371_d_248868659_d_810960823",
    "mode": "",
    "type": "STRING",
    "description": "",
    "fields": []
  },
  {
    "name": "d_703954371_d_248868659_d_861162895",
    "mode": "",
    "type": "STRING",
    "description": "",
    "fields": []
  },
  {
    "name": "d_703954371_d_248868659_d_912088602",
    "mode": "",
    "type": "STRING",
    "description": "",
    "fields": []
  },
  {
    "name": "d_703954371_d_248868659_d_937362785",
    "mode": "",
    "type": "STRING",
    "description": "",
    "fields": []
  },
  {
    "name": "d_703954371_d_248868659_d_982885431",
    "mode": "",
    "type": "STRING",
    "description": "",
    "fields": []
  },
  {
    "name": "d_703954371_d_338286049",
    "mode": "",
    "type": "STRING",
    "description": "",
    "fields": []
  },
  {
    "name": "d_703954371_d_536710547",
    "mode": "",
    "type": "STRING",
    "description": "",
    "fields": []
  },
  {
    "name": "d_703954371_d_593843561",
    "mode": "",
    "type": "STRING",
    "description": "",
    "fields": []
  },
  {
    "name": "d_703954371_d_678857215",
    "mode": "",
    "type": "STRING",
    "description": "",
    "fields": []
  },
  {
    "name": "d_703954371_d_762124027",
    "mode": "",
    "type": "STRING",
    "description": "",
    "fields": []
  },
  {
    "name": "d_703954371_d_825582494",
    "mode": "",
    "type": "STRING",
    "description": "",
    "fields": []
  },
  {
    "name": "d_703954371_d_883732523",
    "mode": "",
    "type": "STRING",
    "description": "",
    "fields": []
  },
  {
    "name": "d_703954371_d_926457119",
    "mode": "",
    "type": "STRING",
    "description": "",
    "fields": []
  },
  {
    "name": "d_719427591",
    "mode": "",
    "type": "STRING",
    "description": "",
    "fields": []
  },
  {
    "name": "d_771580890",
    "mode": "",
    "type": "STRING",
    "description": "",
    "fields": []
  },
  {
    "name": "d_787237543_d_593843561",
    "mode": "",
    "type": "STRING",
    "description": "",
    "fields": []
  },
  {
    "name": "d_787237543_d_678857215",
    "mode": "",
    "type": "STRING",
    "description": "",
    "fields": []
  },
  {
    "name": "d_787237543_d_762124027",
    "mode": "",
    "type": "STRING",
    "description": "",
    "fields": []
  },
  {
    "name": "d_787237543_d_825582494",
    "mode": "",
    "type": "STRING",
    "description": "",
    "fields": []
  },
  {
    "name": "d_820476880",
    "mode": "",
    "type": "STRING",
    "description": "",
    "fields": []
  },
  {
    "name": "d_827220437",
    "mode": "",
    "type": "STRING",
    "description": "",
    "fields": []
  },
  {
    "name": "d_838567176_d_248868659_d_242307474",
    "mode": "",
    "type": "STRING",
    "description": "",
    "fields": []
  },
  {
    "name": "d_838567176_d_248868659_d_283900611",
    "mode": "",
    "type": "STRING",
    "description": "",
    "fields": []
  },
  {
    "name": "d_838567176_d_248868659_d_313097539",
    "mode": "",
    "type": "STRING",
    "description": "",
    "fields": []
  },
  {
    "name": "d_838567176_d_248868659_d_453343022",
    "mode": "",
    "type": "STRING",
    "description": "",
    "fields": []
  },
  {
    "name": "d_838567176_d_248868659_d_472864016",
    "mode": "",
    "type": "STRING",
    "description": "",
    "fields": []
  },
  {
    "name": "d_838567176_d_248868659_d_550088682",
    "mode": "",
    "type": "STRING",
    "description": "",
    "fields": []
  },
  {
    "name": "d_838567176_d_248868659_d_684617815",
    "mode": "",
    "type": "STRING",
    "description": "",
    "fields": []
  },
  {
    "name": "d_838567176_d_248868659_d_690540566",
    "mode": "",
    "type": "STRING",
    "description": "",
    "fields": []
  },
  {
    "name": "d_838567176_d_248868659_d_728366619",
    "mode": "",
    "type": "STRING",
    "description": "",
    "fields": []
  },
  {
    "name": "d_838567176_d_248868659_d_757246707",
    "mode": "",
    "type": "STRING",
    "description": "",
    "fields": []
  },
  {
    "name": "d_838567176_d_248868659_d_777486216",
    "mode": "",
    "type": "STRING",
    "description": "",
    "fields": []
  },
  {
    "name": "d_838567176_d_248868659_d_810960823",
    "mode": "",
    "type": "STRING",
    "description": "",
    "fields": []
  },
  {
    "name": "d_838567176_d_248868659_d_982885431",
    "mode": "",
    "type": "STRING",
    "description": "",
    "fields": []
  },
  {
    "name": "d_838567176_d_338286049",
    "mode": "",
    "type": "STRING",
    "description": "",
    "fields": []
  },
  {
    "name": "d_838567176_d_536710547",
    "mode": "",
    "type": "STRING",
    "description": "",
    "fields": []
  },
  {
    "name": "d_838567176_d_593843561",
    "mode": "",
    "type": "STRING",
    "description": "",
    "fields": []
  },
  {
    "name": "d_838567176_d_678857215",
    "mode": "",
    "type": "STRING",
    "description": "",
    "fields": []
  },
  {
    "name": "d_838567176_d_762124027",
    "mode": "",
    "type": "STRING",
    "description": "",
    "fields": []
  },
  {
    "name": "d_838567176_d_825582494",
    "mode": "",
    "type": "STRING",
    "description": "",
    "fields": []
  },
  {
    "name": "d_838567176_d_883732523",
    "mode": "",
    "type": "STRING",
    "description": "",
    "fields": []
  },
  {
    "name": "d_838567176_d_926457119",
    "mode": "",
    "type": "STRING",
    "description": "",
    "fields": []
  },
  {
    "name": "d_915838974",
    "mode": "",
    "type": "STRING",
    "description": "",
    "fields": []
  },
  {
    "name": "d_926457119",
    "mode": "",
    "type": "STRING",
    "description": "",
    "fields": []
  },
  {
    "name": "d_928693120",
    "mode": "",
    "type": "STRING",
    "description": "",
    "fields": []
  },
  {
    "name": "d_951355211",
    "mode": "",
    "type": "STRING",
    "description": "",
    "fields": []
  },
  {
    "name": "d_958646668_d_248868659_d_242307474",
    "mode": "",
    "type": "STRING",
    "description": "",
    "fields": []
  },
  {
    "name": "d_958646668_d_248868659_d_283900611",
    "mode": "",
    "type": "STRING",
    "description": "",
    "fields": []
  },
  {
    "name": "d_958646668_d_248868659_d_313097539",
    "mode": "",
    "type": "STRING",
    "description": "",
    "fields": []
  },
  {
    "name": "d_958646668_d_248868659_d_453343022",
    "mode": "",
    "type": "STRING",
    "description": "",
    "fields": []
  },
  {
    "name": "d_958646668_d_248868659_d_472864016",
    "mode": "",
    "type": "STRING",
    "description": "",
    "fields": []
  },
  {
    "name": "d_958646668_d_248868659_d_550088682",
    "mode": "",
    "type": "STRING",
    "description": "",
    "fields": []
  },
  {
    "name": "d_958646668_d_248868659_d_684617815",
    "mode": "",
    "type": "STRING",
    "description": "",
    "fields": []
  },
  {
    "name": "d_958646668_d_248868659_d_690540566",
    "mode": "",
    "type": "STRING",
    "description": "",
    "fields": []
  },
  {
    "name": "d_958646668_d_248868659_d_728366619",
    "mode": "",
    "type": "STRING",
    "description": "",
    "fields": []
  },
  {
    "name": "d_958646668_d_248868659_d_757246707",
    "mode": "",
    "type": "STRING",
    "description": "",
    "fields": []
  },
  {
    "name": "d_958646668_d_248868659_d_777486216",
    "mode": "",
    "type": "STRING",
    "description": "",
    "fields": []
  },
  {
    "name": "d_958646668_d_248868659_d_810960823",
    "mode": "",
    "type": "STRING",
    "description": "",
    "fields": []
  },
  {
    "name": "d_958646668_d_248868659_d_982885431",
    "mode": "",
    "type": "STRING",
    "description": "",
    "fields": []
  },
  {
    "name": "d_958646668_d_536710547",
    "mode": "",
    "type": "STRING",
    "description": "",
    "fields": []
  },
  {
    "name": "d_958646668_d_593843561",
    "mode": "",
    "type": "STRING",
    "description": "",
    "fields": []
  },
  {
    "name": "d_958646668_d_678857215",
    "mode": "",
    "type": "STRING",
    "description": "",
    "fields": []
  },
  {
    "name": "d_958646668_d_762124027",
    "mode": "",
    "type": "STRING",
    "description": "",
    "fields": []
  },
  {
    "name": "d_958646668_d_825582494",
    "mode": "",
    "type": "STRING",
    "description": "",
    "fields": []
  },
  {
    "name": "d_958646668_d_926457119",
    "mode": "",
    "type": "STRING",
    "description": "",
    "fields": []
  },
  {
    "name": "d_973670172_d_248868659_d_283900611",
    "mode": "",
    "type": "STRING",
    "description": "",
    "fields": []
  },
  {
    "name": "d_973670172_d_248868659_d_313097539",
    "mode": "",
    "type": "STRING",
    "description": "",
    "fields": []
  },
  {
    "name": "d_973670172_d_248868659_d_453343022",
    "mode": "",
    "type": "STRING",
    "description": "",
    "fields": []
  },
  {
    "name": "d_973670172_d_248868659_d_472864016",
    "mode": "",
    "type": "STRING",
    "description": "",
    "fields": []
  },
  {
    "name": "d_973670172_d_248868659_d_550088682",
    "mode": "",
    "type": "STRING",
    "description": "",
    "fields": []
  },
  {
    "name": "d_973670172_d_248868659_d_684617815",
    "mode": "",
    "type": "STRING",
    "description": "",
    "fields": []
  },
  {
    "name": "d_973670172_d_248868659_d_690540566",
    "mode": "",
    "type": "STRING",
    "description": "",
    "fields": []
  },
  {
    "name": "d_973670172_d_248868659_d_728366619",
    "mode": "",
    "type": "STRING",
    "description": "",
    "fields": []
  },
  {
    "name": "d_973670172_d_248868659_d_757246707",
    "mode": "",
    "type": "STRING",
    "description": "",
    "fields": []
  },
  {
    "name": "d_973670172_d_248868659_d_956345366",
    "mode": "",
    "type": "STRING",
    "description": "",
    "fields": []
  },
  {
    "name": "d_973670172_d_248868659_d_982885431",
    "mode": "",
    "type": "STRING",
    "description": "",
    "fields": []
  },
  {
    "name": "d_973670172_d_338286049",
    "mode": "",
    "type": "STRING",
    "description": "",
    "fields": []
  },
  {
    "name": "d_973670172_d_536710547",
    "mode": "",
    "type": "STRING",
    "description": "",
    "fields": []
  },
  {
    "name": "d_973670172_d_593843561",
    "mode": "",
    "type": "STRING",
    "description": "",
    "fields": []
  },
  {
    "name": "d_973670172_d_678857215",
    "mode": "",
    "type": "STRING",
    "description": "",
    "fields": []
  },
  {
    "name": "d_973670172_d_762124027",
    "mode": "",
    "type": "STRING",
    "description": "",
    "fields": []
  },
  {
    "name": "d_973670172_d_825582494",
    "mode": "",
    "type": "STRING",
    "description": "",
    "fields": []
  },
  {
    "name": "d_973670172_d_883732523",
    "mode": "",
    "type": "STRING",
    "description": "",
    "fields": []
  },
  {
    "name": "d_973670172_d_926457119",
    "mode": "",
    "type": "STRING",
    "description": "",
    "fields": []
  },
  {
    "name": "d_973670172_d_973670172",
    "mode": "",
    "type": "STRING",
    "description": "",
    "fields": []
  }
]